youtubeAPI/__init__.py
youtubeAPI_tjmoon0104-0.2.1.dist-info/LICENSE
youtubeAPI_tjmoon0104-0.2.1.dist-info/METADATA
youtubeAPI_tjmoon0104-0.2.1.dist-info/WHEEL
youtubeAPI_tjmoon0104-0.2.1.dist-info/top_level.txt
youtubeAPI_tjmoon0104-0.2.1.dist-info/RECORD
